Workbook

Sheet Overview and Historicals
A1: ICICI BANK LTD (CONSOLIDATED) — COMPANY OVERVIEW & HISTORICAL FINANCIALS
A2: COMPANY OVERVIEW
A3: ICICI Bank Ltd (Industrial Credit and Investment Corporation of India Bank Ltd)
A4: ICICI Bank is an Indian multinational private bank and financial services company headquartered in Mumbai. It was established in 1955 at the initiative of the World Bank, the Government of India, and representatives of Indian industry. It offers services to corporate and retail customers, and has subsidiaries in investment banking, life and non-life insurance, venture capital, and asset management. Headquarters: Mumbai, Maharashtra Key Subsidiaries: ICICI Prudential (Life Insurance & Asset Management), ICICI Lombard (General Insurance), ICICI Securities / ICICI Direct (Broking & Investment) Network: ~7,500 branches and 12,000+ ATMs/CRMs across India; banking presence in 19 countries Rank: 2nd-largest private sector bank in India (after HDFC Bank); 214th globally
A6: PROFIT & LOSS | H6: KEY RATIOS
A7: Particulars | B7: FY2022 | C7: FY2023 | D7: FY2024 | E7: FY2025 | F7: FY2026 | H7: Metric | I7: Value | J7: As of
A8: Revenue | B8: 95407 | C8: 121067 | D8: 159516 | E8: 186331 | F8: 195218 | H8: Capital Adequacy Ratio (CAR) | I8: 16.84% | J8: Q1 FY27 (Jun-2026)
A9: Interest Expense | B9: 41167 | C9: 50543 | D9: 74108 | E9: 89028 | F9: 89029 | H9: Net Interest Margin (NIM) | I9: 4.36% | J9: Q1 FY27 (Jun-2026)
A10: Net Interest Income (NII) | B10: =B8-B9 -> 54240 | C10: =C8-C9 -> 70524 | D10: =D8-D9 -> 85408 | E10: =E8-E9 -> 97303 | F10: =F8-F9 -> 106189 | H10: Gross NPA % | I10: 1.53% | J10: Q3 FY26 (Dec-2025)
A11: Operating Expenses | B11: 80798 | C11: 87864 | D11: 99560 | E11: 130078 | F11: 142971 | H11: Net NPA % | I11: 0.35% | J11: Q1 FY27 (Jun-2026)
A12: Financing Profit | B12: =B10-B11 -> -26558 | C12: =C10-C11 -> -17340 | D12: =D10-D11 -> -14152 | E12: =E10-E11 -> -32775 | F12: =F10-F11 -> -36782 | H12: CASA Ratio | I12: 39% | J12: Q3 FY26 (Dec-2025)
A13: Other Income | B13: 62129 | C13: 65112 | D13: 76522 | E13: 108255 | F13: 116900 | H13: Return on Equity (ROE) | I13: 15.9% | J13: TTM
A14: Pre-Provision Operating Profit (PPOP) | B14: =B12+B13 -> 35571 | C14: =C12+C13 -> 47772 | D14: =D12+D13 -> 62370 | E14: =E12+E13 -> 75480 | F14: =F12+F13 -> 80118 | H14: Return on Capital Employed (ROCE) | I14: 7.18% | J14: TTM
A15: Depreciation | B15: 1330 | C15: 1515 | D15: 1935 | E15: 2627 | F15: 3061 | H15: Stock P/E | I15: 17.6x | J15: Current
A16: Profit Before Tax | B16: =B14-B15 -> 34241 | C16: =C14-C15 -> 46257 | D16: =D14-D15 -> 60435 | E16: =E14-E15 -> 72853 | F16: =F14-F15 -> 77057 | H16: Book Value / Share | I16: ₹527 | J16: Current
A17: Tax | B17: 8457.44 | C17: 11793.44 | D17: 15427.62 | E17: 18434.83 | F17: 19383.93 | H17: Market Capitalisation | I17: ₹9,90,020 Cr | J17: Current
A18: Minority Interest (NCI share) | B18: 673.46 | C18: 426.92 | D18: 751.01 | E18: 3388.97 | F18: 3465.37 | H18: Dividend Yield | I18: 0.87% | J18: Current
A19: Net Profit (attributable to shareholders) | B19: =B16-B17-B18 -> 25110.1 | C19: =C16-C17-C18 -> 34036.64 | D19: =D16-D17-D18 -> 44256.37 | E19: =E16-E17-E18 -> 51029.2 | F19: =F16-F17-F18 -> 54207.7 | H19: Advances (gross, standalone) | I19: ₹16,31,260 Cr (+19.6% YoY) | J19: Q1 FY27 (Jun-2026)
A20: Equity Shares (Cr) | B20: 694.88 | C20: 698.28 | D20: 702.23 | E20: 712.19 | F20: 716.01
A21: EPS (₹) | B21: =B19/B20 -> 36.13588 | C21: =C19/C20 -> 48.743541 | D21: =D19/D20 -> 63.022614 | E21: =E19/E20 -> 71.651104 | F21: =F19/F20 -> 75.708021
A22: Dividend Payout (%) | B22: 0.14 | C22: 0.16 | D22: 0.16 | E22: 0.15 | F22: 0.16
A24: BALANCE SHEET
A25: Particulars | B25: FY2022 | C25: FY2023 | D25: FY2024 | E25: FY2025 | F25: FY2026
A26: Equity Capital | B26: 1390 | C26: 1397 | D26: 1405 | E26: 1425 | F26: 1432
A27: Reserves | B27: 180663 | C27: 213101 | D27: 254739 | E27: 312481 | F27: 361628
A28: Deposits | B28: 1091366 | C28: 1210832 | D28: 1443580 | E28: 1641637 | F28: 1830020
A29: Borrowings | B29: 161603 | C29: 189062 | D29: 207428 | E29: 218883 | F29: 220264
A30: Other Liabilities | B30: 317616 | C30: 344099 | D30: 456911 | E30: 467815 | F30: 501153
A31: Total Liabilities | B31: =B26+B27+B28+B29+B30 -> 1752638 | C31: =C26+C27+C28+C29+C30 -> 1958491 | D31: =D26+D27+D28+D29+D30 -> 2364063 | E31: =E26+E27+E28+E29+E30 -> 2642241 | F31: =F26+F27+F28+F29+F30 -> 2914497
A32: Fixed Assets (Net Block) | B32: 10707 | C32: 11070 | D32: 15714 | E32: 24272 | F32: 27970
A33: Investments | B33: 567098 | C33: 639552 | D33: 827163 | E33: 886377 | F33: 870720
A34: Other Assets (incl. advances) | B34: 1174833 | C34: 1307868 | D34: 1521186 | E34: 1731593 | F34: 2015808
A35: Total Assets | B35: =B32+B33+B34 -> 1752638 | C35: =C32+C33+C34 -> 1958490 | D35: =D32+D33+D34 -> 2364063 | E35: =E32+E33+E34 -> 2642242 | F35: =F32+F33+F34 -> 2914498
A37: CASH FLOW
A38: Particulars | B38: FY2022 | C38: FY2023 | D38: FY2024 | E38: FY2025 | F38: FY2026
A39: Cash from Operating Activity | B39: 58111 | C39: -3771 | D39: 157284 | E39: 122805 | F39: 67325
A40: Cash from Investing Activity | B40: -40007 | C40: -67689 | D40: -144737 | E40: -77140 | F40: -11708
A41: Cash from Financing Activity | B41: 17451 | C41: 24791 | D41: 13765 | E41: 5589 | F41: -4661
A42: Net Cash Flow | B42: =B39+B40+B41 -> 35555 | C42: =C39+C40+C41 -> -46669 | D42: =D39+D40+D41 -> 26312 | E42: =E39+E40+E41 -> 51254 | F42: =F39+F40+F41 -> 50956

Sheet Dashboard
A1: ICICI BANK LTD — FINANCIAL PLANNING DASHBOARD
A3: SCENARIO SELECTOR HERE
A4: Bull
A8: KEY FINANCIAL KPIs (FY2030-31E, active scenario)
A9: Revenue FY2030-31E | C9: Net Profit FY2030-31E | E9: Revenue CAGR (FY26-31E) | G9: Net Profit CAGR (FY26-31E) | I9: Net Margin FY2030-31E | K9: Cost-to-Income FY2030-31E
A10: =Forecast!F5 -> 446571.4 | C10: =Forecast!F22 -> 205517.26 | E10: =(Forecast!F5/'Overview and Historicals'!$F$8)^(1/5)-1 -> 0.17997881 | G10: =(Forecast!F22/'Overview and Historicals'!$F$19)^(1/5)-1 -> 0.30544165 | I10: =Forecast!F22/Forecast!F5 -> 0.46021143 | K10: =Forecast!F10/(Forecast!F9+Forecast!F12) -> 0.44520288
A13: ="Under the "&A4&" scenario, Revenue is projected to grow from ₹"&TEXT('Overview and Historicals'!$F$8,"#,##0")&" Cr (FY25-26) to ₹"&TEXT(Forecast!F5,"#,##0")&" Cr by FY2030-31E, while Net Profit grows from ₹"&TEXT('Overview and Historicals'!$F$19,"#,##0")&" Cr to ₹"&TEXT(Forecast!F22,"#,##0")&" Cr." -> Under the Bull scenario, Revenue is projected to grow from ₹1,95,218 Cr (FY25-26) to ₹4,46,571 Cr by FY2030-31E, while Net Profit grows from ₹54,208 Cr to ₹2,05,517 Cr.
A15: Year | B15: FY2022-23 | C15: FY2023-24 | D15: FY2024-25 | E15: FY2025-26 | F15: FY2026-27 | G15: FY2027-28 | H15: FY2028-29 | I15: FY2029-30 | J15: FY2030-31
A16: Revenue (₹ Cr) | B16: ='Overview and Historicals'!C8 -> 121067 | C16: ='Overview and Historicals'!D8 -> 159516 | D16: ='Overview and Historicals'!E8 -> 186331 | E16: ='Overview and Historicals'!F8 -> 195218 | F16: =Forecast!B5 -> 232309.42 | G16: =Forecast!C5 -> 275286.66 | H16: =Forecast!D5 -> 324838.26 | I16: =Forecast!E5 -> 381684.96 | J16: =Forecast!F5 -> 446571.4
A17: Net Profit (₹ Cr) | B17: ='Overview and Historicals'!C19 -> 34036.64 | C17: ='Overview and Historicals'!D19 -> 44256.37 | D17: ='Overview and Historicals'!E19 -> 51029.2 | E17: ='Overview and Historicals'!F19 -> 54207.7 | F17: =Forecast!B22 -> 75037.253 | G17: =Forecast!C22 -> 99978.319 | H17: =Forecast!D22 -> 129722.21 | I17: =Forecast!E22 -> 164749.39 | J17: =Forecast!F22 -> 205517.26
A18: PPOP Margin % | B18: ='Overview and Historicals'!C14/'Overview and Historicals'!C8 -> 0.39459142 | C18: ='Overview and Historicals'!D14/'Overview and Historicals'!D8 -> 0.39099526 | D18: ='Overview and Historicals'!E14/'Overview and Historicals'!E8 -> 0.40508557 | E18: ='Overview and Historicals'!F14/'Overview and Historicals'!F8 -> 0.41040273 | F18: =Forecast!B14/Forecast!B5 -> 0.46881246 | G18: =Forecast!C14/Forecast!C5 -> 0.52478808 | H18: =Forecast!D14/Forecast!D5 -> 0.57520783 | I18: =Forecast!E14/Forecast!E5 -> 0.62025839 | J18: =Forecast!F14/Forecast!F5 -> 0.66015112
A19: Net Margin % | B19: ='Overview and Historicals'!C19/'Overview and Historicals'!C8 -> 0.28113887 | C19: ='Overview and Historicals'!D19/'Overview and Historicals'!D8 -> 0.27744157 | D19: ='Overview and Historicals'!E19/'Overview and Historicals'!E8 -> 0.27386318 | E19: ='Overview and Historicals'!F19/'Overview and Historicals'!F8 -> 0.27767778 | F19: =Forecast!B22/Forecast!B5 -> 0.32300564 | G19: =Forecast!C22/Forecast!C5 -> 0.36317894 | H19: =Forecast!D22/Forecast!D5 -> 0.39934399 | I19: =Forecast!E22/Forecast!E5 -> 0.4316371 | J19: =Forecast!F22/Forecast!F5 -> 0.46021143

Sheet Assumptions
A1: FORECAST ASSUMPTIONS & SCENARIO DRIVERS (FY2026-27E–FY2030-31E)
A4: Active scenario (set on Dashboard tab) → | C4: =Dashboard!$A$4 -> Bull
A7: BASE CASE (most likely — in line with consensus) | H7: BULL CASE (credit up-cycle sustained, benign asset quality) | O7: BEAR CASE (systemic slowdown, NIM & asset-quality pressure)
A8: Driver | B8: FY2026-27 | C8: FY2027-28 | D8: FY2028-29 | E8: FY2029-30 | F8: FY2030-31 | H8: Driver | I8: FY2026-27 | J8: FY2027-28 | K8: FY2028-29 | L8: FY2029-30 | M8: FY2030-31 | O8: Driver | P8: FY2026-27 | Q8: FY2027-28 | R8: FY2028-29 | S8: FY2029-30 | T8: FY2030-31
A9: Revenue growth % | B9: 0.155 | C9: 0.15 | D9: 0.145 | E9: 0.14 | F9: 0.135 | H9: Revenue growth % | I9: 0.19 | J9: 0.185 | K9: 0.18 | L9: 0.175 | M9: 0.17 | O9: Revenue growth % | P9: 0.1 | Q9: 0.09 | R9: 0.085 | S9: 0.08 | T9: 0.08
A10: Interest Expense growth % | B10: 0.135 | C10: 0.13 | D10: 0.125 | E10: 0.125 | F10: 0.12 | H10: Interest Expense growth % | I10: 0.15 | J10: 0.145 | K10: 0.14 | L10: 0.135 | M10: 0.13 | O10: Interest Expense growth % | P10: 0.12 | Q10: 0.12 | R10: 0.115 | S10: 0.11 | T10: 0.11
A11: Operating Expense growth % | B11: 0.13 | C11: 0.12 | D11: 0.115 | E11: 0.11 | F11: 0.105 | H11: Operating Expense growth % | I11: 0.12 | J11: 0.11 | K11: 0.105 | L11: 0.1 | M11: 0.095 | O11: Operating Expense growth % | P11: 0.13 | Q11: 0.13 | R11: 0.125 | S11: 0.12 | T11: 0.12
A12: Other Income growth % | B12: 0.15 | C12: 0.14 | D12: 0.135 | E12: 0.13 | F12: 0.125 | H12: Other Income growth % | I12: 0.19 | J12: 0.18 | K12: 0.17 | L12: 0.16 | M12: 0.15 | O12: Other Income growth % | P12: 0.09 | Q12: 0.08 | R12: 0.08 | S12: 0.075 | T12: 0.07
A13: Depreciation growth % | B13: 0.14 | C13: 0.14 | D13: 0.14 | E13: 0.14 | F13: 0.14 | H13: Depreciation growth % | I13: 0.15 | J13: 0.15 | K13: 0.15 | L13: 0.15 | M13: 0.15 | O13: Depreciation growth % | P13: 0.13 | Q13: 0.13 | R13: 0.13 | S13: 0.13 | T13: 0.13
A14: Effective Tax Rate % | B14: 0.25 | C14: 0.25 | D14: 0.25 | E14: 0.25 | F14: 0.25 | H14: Effective Tax Rate % | I14: 0.24 | J14: 0.24 | K14: 0.24 | L14: 0.24 | M14: 0.24 | O14: Effective Tax Rate % | P14: 0.26 | Q14: 0.26 | R14: 0.26 | S14: 0.26 | T14: 0.26
A15: Minority Interest (% of PBT) | B15: 0.045 | C15: 0.045 | D15: 0.045 | E15: 0.045 | F15: 0.045 | H15: Minority Interest (% of PBT) | I15: 0.048 | J15: 0.048 | K15: 0.048 | L15: 0.048 | M15: 0.048 | O15: Minority Interest (% of PBT) | P15: 0.04 | Q15: 0.04 | R15: 0.04 | S15: 0.04 | T15: 0.04
A16: Dividend Payout % | B16: 0.16 | C16: 0.16 | D16: 0.16 | E16: 0.16 | F16: 0.16 | H16: Dividend Payout % | I16: 0.17 | J16: 0.17 | K16: 0.17 | L16: 0.17 | M16: 0.17 | O16: Dividend Payout % | P16: 0.14 | Q16: 0.14 | R16: 0.14 | S16: 0.14 | T16: 0.14
A19: ACTIVE ASSUMPTIONS (auto-selected per Dashboard scenario selector)
A20: Driver | B20: FY2026-27 | C20: FY2027-28 | D20: FY2028-29 | E20: FY2029-30 | F20: FY2030-31
A21: Revenue growth % | B21: =IF(Assumptions!$C$4="Base",B9,IF(Assumptions!$C$4="Bull",I9,P9)) -> 0.19 | C21: =IF(Assumptions!$C$4="Base",C9,IF(Assumptions!$C$4="Bull",J9,Q9)) -> 0.185 | D21: =IF(Assumptions!$C$4="Base",D9,IF(Assumptions!$C$4="Bull",K9,R9)) -> 0.18 | E21: =IF(Assumptions!$C$4="Base",E9,IF(Assumptions!$C$4="Bull",L9,S9)) -> 0.175 | F21: =IF(Assumptions!$C$4="Base",F9,IF(Assumptions!$C$4="Bull",M9,T9)) -> 0.17
A22: Interest Expense growth % | B22: =IF(Assumptions!$C$4="Base",B10,IF(Assumptions!$C$4="Bull",I10,P10)) -> 0.15 | C22: =IF(Assumptions!$C$4="Base",C10,IF(Assumptions!$C$4="Bull",J10,Q10)) -> 0.145 | D22: =IF(Assumptions!$C$4="Base",D10,IF(Assumptions!$C$4="Bull",K10,R10)) -> 0.14 | E22: =IF(Assumptions!$C$4="Base",E10,IF(Assumptions!$C$4="Bull",L10,S10)) -> 0.135 | F22: =IF(Assumptions!$C$4="Base",F10,IF(Assumptions!$C$4="Bull",M10,T10)) -> 0.13
A23: Operating Expense growth % | B23: =IF(Assumptions!$C$4="Base",B11,IF(Assumptions!$C$4="Bull",I11,P11)) -> 0.12 | C23: =IF(Assumptions!$C$4="Base",C11,IF(Assumptions!$C$4="Bull",J11,Q11)) -> 0.11 | D23: =IF(Assumptions!$C$4="Base",D11,IF(Assumptions!$C$4="Bull",K11,R11)) -> 0.105 | E23: =IF(Assumptions!$C$4="Base",E11,IF(Assumptions!$C$4="Bull",L11,S11)) -> 0.1 | F23: =IF(Assumptions!$C$4="Base",F11,IF(Assumptions!$C$4="Bull",M11,T11)) -> 0.095
A24: Other Income growth % | B24: =IF(Assumptions!$C$4="Base",B12,IF(Assumptions!$C$4="Bull",I12,P12)) -> 0.19 | C24: =IF(Assumptions!$C$4="Base",C12,IF(Assumptions!$C$4="Bull",J12,Q12)) -> 0.18 | D24: =IF(Assumptions!$C$4="Base",D12,IF(Assumptions!$C$4="Bull",K12,R12)) -> 0.17 | E24: =IF(Assumptions!$C$4="Base",E12,IF(Assumptions!$C$4="Bull",L12,S12)) -> 0.16 | F24: =IF(Assumptions!$C$4="Base",F12,IF(Assumptions!$C$4="Bull",M12,T12)) -> 0.15
A25: Depreciation growth % | B25: =IF(Assumptions!$C$4="Base",B13,IF(Assumptions!$C$4="Bull",I13,P13)) -> 0.15 | C25: =IF(Assumptions!$C$4="Base",C13,IF(Assumptions!$C$4="Bull",J13,Q13)) -> 0.15 | D25: =IF(Assumptions!$C$4="Base",D13,IF(Assumptions!$C$4="Bull",K13,R13)) -> 0.15 | E25: =IF(Assumptions!$C$4="Base",E13,IF(Assumptions!$C$4="Bull",L13,S13)) -> 0.15 | F25: =IF(Assumptions!$C$4="Base",F13,IF(Assumptions!$C$4="Bull",M13,T13)) -> 0.15
A26: Effective Tax Rate % | B26: =IF(Assumptions!$C$4="Base",B14,IF(Assumptions!$C$4="Bull",I14,P14)) -> 0.24 | C26: =IF(Assumptions!$C$4="Base",C14,IF(Assumptions!$C$4="Bull",J14,Q14)) -> 0.24 | D26: =IF(Assumptions!$C$4="Base",D14,IF(Assumptions!$C$4="Bull",K14,R14)) -> 0.24 | E26: =IF(Assumptions!$C$4="Base",E14,IF(Assumptions!$C$4="Bull",L14,S14)) -> 0.24 | F26: =IF(Assumptions!$C$4="Base",F14,IF(Assumptions!$C$4="Bull",M14,T14)) -> 0.24
A27: Minority Interest (% of PBT) | B27: =IF(Assumptions!$C$4="Base",B15,IF(Assumptions!$C$4="Bull",I15,P15)) -> 0.048 | C27: =IF(Assumptions!$C$4="Base",C15,IF(Assumptions!$C$4="Bull",J15,Q15)) -> 0.048 | D27: =IF(Assumptions!$C$4="Base",D15,IF(Assumptions!$C$4="Bull",K15,R15)) -> 0.048 | E27: =IF(Assumptions!$C$4="Base",E15,IF(Assumptions!$C$4="Bull",L15,S15)) -> 0.048 | F27: =IF(Assumptions!$C$4="Base",F15,IF(Assumptions!$C$4="Bull",M15,T15)) -> 0.048
A28: Dividend Payout % | B28: =IF(Assumptions!$C$4="Base",B16,IF(Assumptions!$C$4="Bull",I16,P16)) -> 0.17 | C28: =IF(Assumptions!$C$4="Base",C16,IF(Assumptions!$C$4="Bull",J16,Q16)) -> 0.17 | D28: =IF(Assumptions!$C$4="Base",D16,IF(Assumptions!$C$4="Bull",K16,R16)) -> 0.17 | E28: =IF(Assumptions!$C$4="Base",E16,IF(Assumptions!$C$4="Bull",L16,S16)) -> 0.17 | F28: =IF(Assumptions!$C$4="Base",F16,IF(Assumptions!$C$4="Bull",M16,T16)) -> 0.17

Sheet Forecast
A1: ICICI BANK LTD (CONSOLIDATED) — REVENUE, EXPENDITURE & PROFITABILITY FORECAST
A2: ="Active scenario: "&Dashboard!$A$4&" | All figures ₹ Crore, consolidated basis, FY ends 31-Mar" -> Active scenario: Bull | All figures ₹ Crore, consolidated basis, FY ends 31-Mar
A4: Particulars | B4: FY2026-27 | C4: FY2027-28 | D4: FY2028-29 | E4: FY2029-30 | F4: FY2030-31
A5: Revenue | B5: ='Overview and Historicals'!$F$8*(1+Assumptions!B21) -> 232309.42 | C5: =B5*(1+Assumptions!C21) -> 275286.66 | D5: =C5*(1+Assumptions!D21) -> 324838.26 | E5: =D5*(1+Assumptions!E21) -> 381684.96 | F5: =E5*(1+Assumptions!F21) -> 446571.4
A6: YoY growth % (memo) | B6: =B5/'Overview and Historicals'!$F$8-1 -> 0.19 | C6: =C5/B5-1 -> 0.185 | D6: =D5/C5-1 -> 0.18 | E6: =E5/D5-1 -> 0.175 | F6: =F5/E5-1 -> 0.17
A7: Interest Expense | B7: ='Overview and Historicals'!$F$9*(1+Assumptions!B22) -> 102383.35 | C7: =B7*(1+Assumptions!C22) -> 117228.94 | D7: =C7*(1+Assumptions!D22) -> 133640.99 | E7: =D7*(1+Assumptions!E22) -> 151682.52 | F7: =E7*(1+Assumptions!F22) -> 171401.25
A8: YoY growth % (memo) | B8: =B7/'Overview and Historicals'!$F$9-1 -> 0.15 | C8: =C7/B7-1 -> 0.145 | D8: =D7/C7-1 -> 0.14 | E8: =E7/D7-1 -> 0.135 | F8: =F7/E7-1 -> 0.13
A9: Net Interest Income (NII) | B9: =B5-B7 -> 129926.07 | C9: =C5-C7 -> 158057.73 | D9: =D5-D7 -> 191197.28 | E9: =E5-E7 -> 230002.44 | F9: =F5-F7 -> 275170.15
A10: Operating Expenses | B10: ='Overview and Historicals'!$F$11*(1+Assumptions!B23) -> 160127.52 | C10: =B10*(1+Assumptions!C23) -> 177741.55 | D10: =C10*(1+Assumptions!D23) -> 196404.41 | E10: =D10*(1+Assumptions!E23) -> 216044.85 | F10: =E10*(1+Assumptions!F23) -> 236569.11
A11: YoY growth % (memo) | B11: =B10/'Overview and Historicals'!$F$11-1 -> 0.12 | C11: =C10/B10-1 -> 0.11 | D11: =D10/C10-1 -> 0.105 | E11: =E10/D10-1 -> 0.1 | F11: =F10/E10-1 -> 0.095
A12: Other Income | B12: ='Overview and Historicals'!$F$13*(1+Assumptions!B24) -> 139111 | C12: =B12*(1+Assumptions!C24) -> 164150.98 | D12: =C12*(1+Assumptions!D24) -> 192056.65 | E12: =D12*(1+Assumptions!E24) -> 222785.71 | F12: =E12*(1+Assumptions!F24) -> 256203.57
A13: YoY growth % (memo) | B13: =B12/'Overview and Historicals'!$F$13-1 -> 0.19 | C13: =C12/B12-1 -> 0.18 | D13: =D12/C12-1 -> 0.17 | E13: =E12/D12-1 -> 0.16 | F13: =F12/E12-1 -> 0.15
A14: Pre-Provision Operating Profit (PPOP) | B14: =B9-B10+B12 -> 108909.55 | C14: =C9-C10+C12 -> 144467.16 | D14: =D9-D10+D12 -> 186849.51 | E14: =E9-E10+E12 -> 236743.3 | F14: =F9-F10+F12 -> 294804.61
A15: PPOP Margin % (memo, bank-EBITDA equivalent) | B15: =B14/B5 -> 0.46881246 | C15: =C14/C5 -> 0.52478808 | D15: =D14/D5 -> 0.57520783 | E15: =E14/E5 -> 0.62025839 | F15: =F14/F5 -> 0.66015112
A16: Cost-to-Income % (memo) | B16: =B10/(B9+B12) -> 0.59518757 | C16: =C10/(C9+C12) -> 0.55163484 | D16: =D10/(D9+D12) -> 0.51246549 | E16: =E10/(E9+E12) -> 0.47714334 | F16: =F10/(F9+F12) -> 0.44520288
A17: Depreciation | B17: ='Overview and Historicals'!$F$15*(1+Assumptions!B25) -> 3520.15 | C17: =B17*(1+Assumptions!C25) -> 4048.1725 | D17: =C17*(1+Assumptions!D25) -> 4655.3984 | E17: =D17*(1+Assumptions!E25) -> 5353.7081 | F17: =E17*(1+Assumptions!F25) -> 6156.7644
A18: Profit Before Tax (PBT) | B18: =B14-B17 -> 105389.4 | C18: =C14-C17 -> 140418.99 | D18: =D14-D17 -> 182194.11 | E18: =E14-E17 -> 231389.59 | F18: =F14-F17 -> 288647.84
A19: PBT Margin % (memo) | B19: =B18/B5 -> 0.45365961 | C19: =C18/C5 -> 0.51008278 | D19: =D18/D5 -> 0.5608764 | E19: =E18/E5 -> 0.60623188 | F19: =F18/F5 -> 0.64636437
A20: Tax | B20: =B18*Assumptions!B26 -> 25293.456 | C20: =C18*Assumptions!C26 -> 33700.557 | D20: =D18*Assumptions!D26 -> 43726.587 | E20: =E18*Assumptions!E26 -> 55533.501 | F20: =F18*Assumptions!F26 -> 69275.483
A21: Minority Interest (NCI share) | B21: =B18*Assumptions!B27 -> 5058.6912 | C21: =C18*Assumptions!C27 -> 6740.1114 | D21: =D18*Assumptions!D27 -> 8745.3175 | E21: =E18*Assumptions!E27 -> 11106.7 | F21: =F18*Assumptions!F27 -> 13855.097
A22: Net Profit (attributable to shareholders) | B22: =B18-B20-B21 -> 75037.253 | C22: =C18-C20-C21 -> 99978.319 | D22: =D18-D20-D21 -> 129722.21 | E22: =E18-E20-E21 -> 164749.39 | F22: =F18-F20-F21 -> 205517.26
A23: Net Margin % (memo) | B23: =B22/B5 -> 0.32300564 | C23: =C22/C5 -> 0.36317894 | D23: =D22/D5 -> 0.39934399 | E23: =E22/E5 -> 0.4316371 | F23: =F22/F5 -> 0.46021143
A24: Shares Outstanding (Cr, held flat at FY25-26 actual) | B24: ='Overview and Historicals'!$F$20 -> 716.01 | C24: ='Overview and Historicals'!$F$20 -> 716.01 | D24: ='Overview and Historicals'!$F$20 -> 716.01 | E24: ='Overview and Historicals'!$F$20 -> 716.01 | F24: ='Overview and Historicals'!$F$20 -> 716.01
A25: EPS (₹) | B25: =B22/B24 -> 104.79917 | C25: =C22/C24 -> 139.63257 | D25: =D22/D24 -> 181.17374 | E25: =E22/E24 -> 230.0937 | F25: =F22/F24 -> 287.03128
A26: YoY growth % (memo) | B26: =B25/'Overview and Historicals'!$F$21-1 -> 0.3842545 | C26: =C25/B25-1 -> 0.33238245 | D26: =D25/C25-1 -> 0.2975034 | E26: =E25/D25-1 -> 0.27001682 | F26: =F25/E25-1 -> 0.24745389

Sheet Scenario Analysis
A1: SCENARIO ANALYSIS — BASE vs BULL vs BEAR (FY2026-27E–FY2030-31E)
A3: BASE CASE | H3: BULL CASE | O3: BEAR CASE
A4: Particulars | B4: FY2026-27 | C4: FY2027-28 | D4: FY2028-29 | E4: FY2029-30 | F4: FY2030-31 | H4: Particulars | I4: FY2026-27 | J4: FY2027-28 | K4: FY2028-29 | L4: FY2029-30 | M4: FY2030-31 | O4: Particulars | P4: FY2026-27 | Q4: FY2027-28 | R4: FY2028-29 | S4: FY2029-30 | T4: FY2030-31
A5: Revenue | B5: ='Overview and Historicals'!$F$8*(1+Assumptions!B9) -> 225476.79 | C5: =B5*(1+Assumptions!C9) -> 259298.31 | D5: =C5*(1+Assumptions!D9) -> 296896.56 | E5: =D5*(1+Assumptions!E9) -> 338462.08 | F5: =E5*(1+Assumptions!F9) -> 384154.46 | H5: Revenue | I5: ='Overview and Historicals'!$F$8*(1+Assumptions!I9) -> 232309.42 | J5: =I5*(1+Assumptions!J9) -> 275286.66 | K5: =J5*(1+Assumptions!K9) -> 324838.26 | L5: =K5*(1+Assumptions!L9) -> 381684.96 | M5: =L5*(1+Assumptions!M9) -> 446571.4 | O5: Revenue | P5: ='Overview and Historicals'!$F$8*(1+Assumptions!P9) -> 214739.8 | Q5: =P5*(1+Assumptions!Q9) -> 234066.38 | R5: =Q5*(1+Assumptions!R9) -> 253962.02 | S5: =R5*(1+Assumptions!S9) -> 274278.99 | T5: =S5*(1+Assumptions!T9) -> 296221.31
A6: Interest Expense | B6: ='Overview and Historicals'!$F$9*(1+Assumptions!B10) -> 101047.91 | C6: =B6*(1+Assumptions!C10) -> 114184.14 | D6: =C6*(1+Assumptions!D10) -> 128457.16 | E6: =D6*(1+Assumptions!E10) -> 144514.31 | F6: =E6*(1+Assumptions!F10) -> 161856.02 | H6: Interest Expense | I6: ='Overview and Historicals'!$F$9*(1+Assumptions!I10) -> 102383.35 | J6: =I6*(1+Assumptions!J10) -> 117228.94 | K6: =J6*(1+Assumptions!K10) -> 133640.99 | L6: =K6*(1+Assumptions!L10) -> 151682.52 | M6: =L6*(1+Assumptions!M10) -> 171401.25 | O6: Interest Expense | P6: ='Overview and Historicals'!$F$9*(1+Assumptions!P10) -> 99712.48 | Q6: =P6*(1+Assumptions!Q10) -> 111677.98 | R6: =Q6*(1+Assumptions!R10) -> 124520.95 | S6: =R6*(1+Assumptions!S10) -> 138218.25 | T6: =S6*(1+Assumptions!T10) -> 153422.26
A7: Operating Expenses | B7: ='Overview and Historicals'!$F$11*(1+Assumptions!B11) -> 161557.23 | C7: =B7*(1+Assumptions!C11) -> 180944.1 | D7: =C7*(1+Assumptions!D11) -> 201752.67 | E7: =D7*(1+Assumptions!E11) -> 223945.46 | F7: =E7*(1+Assumptions!F11) -> 247459.74 | H7: Operating Expenses | I7: ='Overview and Historicals'!$F$11*(1+Assumptions!I11) -> 160127.52 | J7: =I7*(1+Assumptions!J11) -> 177741.55 | K7: =J7*(1+Assumptions!K11) -> 196404.41 | L7: =K7*(1+Assumptions!L11) -> 216044.85 | M7: =L7*(1+Assumptions!M11) -> 236569.11 | O7: Operating Expenses | P7: ='Overview and Historicals'!$F$11*(1+Assumptions!P11) -> 161557.23 | Q7: =P7*(1+Assumptions!Q11) -> 182559.67 | R7: =Q7*(1+Assumptions!R11) -> 205379.63 | S7: =R7*(1+Assumptions!S11) -> 230025.18 | T7: =S7*(1+Assumptions!T11) -> 257628.21
A8: Other Income | B8: ='Overview and Historicals'!$F$13*(1+Assumptions!B12) -> 134435 | C8: =B8*(1+Assumptions!C12) -> 153255.9 | D8: =C8*(1+Assumptions!D12) -> 173945.45 | E8: =D8*(1+Assumptions!E12) -> 196558.35 | F8: =E8*(1+Assumptions!F12) -> 221128.15 | H8: Other Income | I8: ='Overview and Historicals'!$F$13*(1+Assumptions!I12) -> 139111 | J8: =I8*(1+Assumptions!J12) -> 164150.98 | K8: =J8*(1+Assumptions!K12) -> 192056.65 | L8: =K8*(1+Assumptions!L12) -> 222785.71 | M8: =L8*(1+Assumptions!M12) -> 256203.57 | O8: Other Income | P8: ='Overview and Historicals'!$F$13*(1+Assumptions!P12) -> 127421 | Q8: =P8*(1+Assumptions!Q12) -> 137614.68 | R8: =Q8*(1+Assumptions!R12) -> 148623.85 | S8: =R8*(1+Assumptions!S12) -> 159770.64 | T8: =S8*(1+Assumptions!T12) -> 170954.59
A9: Depreciation | B9: ='Overview and Historicals'!$F$15*(1+Assumptions!B13) -> 3489.54 | C9: =B9*(1+Assumptions!C13) -> 3978.0756 | D9: =C9*(1+Assumptions!D13) -> 4535.0062 | E9: =D9*(1+Assumptions!E13) -> 5169.907 | F9: =E9*(1+Assumptions!F13) -> 5893.694 | H9: Depreciation | I9: ='Overview and Historicals'!$F$15*(1+Assumptions!I13) -> 3520.15 | J9: =I9*(1+Assumptions!J13) -> 4048.1725 | K9: =J9*(1+Assumptions!K13) -> 4655.3984 | L9: =K9*(1+Assumptions!L13) -> 5353.7081 | M9: =L9*(1+Assumptions!M13) -> 6156.7644 | O9: Depreciation | P9: ='Overview and Historicals'!$F$15*(1+Assumptions!P13) -> 3458.93 | Q9: =P9*(1+Assumptions!Q13) -> 3908.5909 | R9: =Q9*(1+Assumptions!R13) -> 4416.7077 | S9: =R9*(1+Assumptions!S13) -> 4990.8797 | T9: =S9*(1+Assumptions!T13) -> 5639.6941
A10: Net Interest Income (NII) | B10: =B5-B6 -> 124428.88 | C10: =C5-C6 -> 145114.16 | D10: =D5-D6 -> 168439.4 | E10: =E5-E6 -> 193947.77 | F10: =F5-F6 -> 222298.44 | H10: Net Interest Income (NII) | I10: =I5-I6 -> 129926.07 | J10: =J5-J6 -> 158057.73 | K10: =K5-K6 -> 191197.28 | L10: =L5-L6 -> 230002.44 | M10: =M5-M6 -> 275170.15 | O10: Net Interest Income (NII) | P10: =P5-P6 -> 115027.32 | Q10: =Q5-Q6 -> 122388.4 | R10: =R5-R6 -> 129441.08 | S10: =S5-S6 -> 136060.74 | T10: =T5-T6 -> 142799.05
A11: PPOP (bank-EBITDA equiv.) | B11: =B10-B7+B8 -> 97306.645 | C11: =C10-C7+C8 -> 117425.97 | D11: =D10-D7+D8 -> 140632.18 | E11: =E10-E7+E8 -> 166560.67 | F11: =F10-F7+F8 -> 195966.85 | H11: PPOP (bank-EBITDA equiv.) | I11: =I10-I7+I8 -> 108909.55 | J11: =J10-J7+J8 -> 144467.16 | K11: =K10-K7+K8 -> 186849.51 | L11: =L10-L7+L8 -> 236743.3 | M11: =M10-M7+M8 -> 294804.61 | O11: PPOP (bank-EBITDA equiv.) | P11: =P10-P7+P8 -> 80891.09 | Q11: =Q10-Q7+Q8 -> 77443.415 | R11: =R10-R7+R8 -> 72685.305 | S11: =S10-S7+S8 -> 65806.197 | T11: =T10-T7+T8 -> 56125.431
A12: Profit Before Tax | B12: =B11-B9 -> 93817.105 | C12: =C11-C9 -> 113447.89 | D12: =D11-D9 -> 136097.17 | E12: =E11-E9 -> 161390.76 | F12: =F11-F9 -> 190073.16 | H12: Profit Before Tax | I12: =I11-I9 -> 105389.4 | J12: =J11-J9 -> 140418.99 | K12: =K11-K9 -> 182194.11 | L12: =L11-L9 -> 231389.59 | M12: =M11-M9 -> 288647.84 | O12: Profit Before Tax | P12: =P11-P9 -> 77432.16 | Q12: =Q11-Q9 -> 73534.824 | R12: =R11-R9 -> 68268.597 | S12: =S11-S9 -> 60815.317 | T12: =T11-T9 -> 50485.737
A13: Tax | B13: =B12*Assumptions!B14 -> 23454.276 | C13: =C12*Assumptions!C14 -> 28361.973 | D13: =D12*Assumptions!D14 -> 34024.293 | E13: =E12*Assumptions!E14 -> 40347.69 | F13: =F12*Assumptions!F14 -> 47518.289 | H13: Tax | I13: =I12*Assumptions!I14 -> 25293.456 | J13: =J12*Assumptions!J14 -> 33700.557 | K13: =K12*Assumptions!K14 -> 43726.587 | L13: =L12*Assumptions!L14 -> 55533.501 | M13: =M12*Assumptions!M14 -> 69275.483 | O13: Tax | P13: =P12*Assumptions!P14 -> 20132.362 | Q13: =Q12*Assumptions!Q14 -> 19119.054 | R13: =R12*Assumptions!R14 -> 17749.835 | S13: =S12*Assumptions!S14 -> 15811.982 | T13: =T12*Assumptions!T14 -> 13126.292
A14: Minority Interest | B14: =B12*Assumptions!B15 -> 4221.7697 | C14: =C12*Assumptions!C15 -> 5105.1551 | D14: =D12*Assumptions!D15 -> 6124.3728 | E14: =E12*Assumptions!E15 -> 7262.5842 | F14: =F12*Assumptions!F15 -> 8553.2921 | H14: Minority Interest | I14: =I12*Assumptions!I15 -> 5058.6912 | J14: =J12*Assumptions!J15 -> 6740.1114 | K14: =K12*Assumptions!K15 -> 8745.3175 | L14: =L12*Assumptions!L15 -> 11106.7 | M14: =M12*Assumptions!M15 -> 13855.097 | O14: Minority Interest | P14: =P12*Assumptions!P15 -> 3097.2864 | Q14: =Q12*Assumptions!Q15 -> 2941.3929 | R14: =R12*Assumptions!R15 -> 2730.7439 | S14: =S12*Assumptions!S15 -> 2432.6127 | T14: =T12*Assumptions!T15 -> 2019.4295
A15: Net Profit (attributable) | B15: =B12-B13-B14 -> 66141.059 | C15: =C12-C13-C14 -> 79980.763 | D15: =D12-D13-D14 -> 95948.507 | E15: =E12-E13-E14 -> 113780.49 | F15: =F12-F13-F14 -> 134001.58 | H15: Net Profit (attributable) | I15: =I12-I13-I14 -> 75037.253 | J15: =J12-J13-J14 -> 99978.319 | K15: =K12-K13-K14 -> 129722.21 | L15: =L12-L13-L14 -> 164749.39 | M15: =M12-M13-M14 -> 205517.26 | O15: Net Profit (attributable) | P15: =P12-P13-P14 -> 54202.512 | Q15: =Q12-Q13-Q14 -> 51474.377 | R15: =R12-R13-R14 -> 47788.018 | S15: =S12-S13-S14 -> 42570.722 | T15: =T12-T13-T14 -> 35340.016
A16: Net Margin % (memo) | B16: =B15/B5 -> 0.29333866 | C16: =C15/C5 -> 0.30845077 | D16: =D15/D5 -> 0.3231715 | E16: =E15/E5 -> 0.33616908 | F16: =F15/F5 -> 0.34882213 | H16: Net Margin % (memo) | I16: =I15/I5 -> 0.32300564 | J16: =J15/J5 -> 0.36317894 | K16: =K15/K5 -> 0.39934399 | L16: =L15/L5 -> 0.4316371 | M16: =M15/M5 -> 0.46021143 | O16: Net Margin % (memo) | P16: =P15/P5 -> 0.25241018 | Q16: =Q15/Q5 -> 0.21991358 | R16: =R15/R5 -> 0.18816994 | S16: =S15/S5 -> 0.15520956 | T16: =T15/T5 -> 0.11930275
A25: FY2030-31E SUMMARY — SIDE-BY-SIDE COMPARISON
A26: Metric | B26: Base Case | C26: Bull Case | D26: Bear Case
A27: Revenue (₹ Cr) | B27: =F5 -> 384154.46 | C27: =M5 -> 446571.4 | D27: =T5 -> 296221.31
A28: PPOP (₹ Cr) | B28: =F11 -> 195966.85 | C28: =M11 -> 294804.61 | D28: =T11 -> 56125.431
A29: Net Profit (₹ Cr) | B29: =F15 -> 134001.58 | C29: =M15 -> 205517.26 | D29: =T15 -> 35340.016
A30: Net Margin % (FY2030-31E) | B30: =F15/F5 -> 0.34882213 | C30: =M15/M5 -> 0.46021143 | D30: =T15/T5 -> 0.11930275
A31: Net Profit CAGR, FY25-26 to FY30-31E | B31: =(F15/'Overview and Historicals'!$F$19)^(1/5)-1 -> 0.19842203 | C31: =(M15/'Overview and Historicals'!$F$19)^(1/5)-1 -> 0.30544165 | D31: =(T15/'Overview and Historicals'!$F$19)^(1/5)-1 -> -0.082003232

Sheet Management Recommendation
B2: MANAGEMENT RECOMMENDATION
B5: 1. Headline (auto-updates with the Dashboard scenario selector)
B6: ="Under the "&Dashboard!$A$4&" scenario, ICICI Bank's consolidated Revenue is projected to grow from ₹"&TEXT('Overview and Historicals'!$F$8,"#,##0")&" Cr (FY25-26) to ₹"&TEXT(Forecast!F5,"#,##0")&" Cr by FY30-31E ("&TEXT((Forecast!F5/'Overview and Historicals'!$F$8)^(1/5)-1,"0.0%")&" CAGR), while Net Profit (attributable) grows from ₹"&TEXT('Overview and Historicals'!$F$19,"#,##0")&" Cr to ₹"&TEXT(Forecast!F22,"#,##0")&" Cr ("&TEXT((Forecast!F22/'Overview and Historicals'!$F$19)^(1/5)-1,"0.0%")&" CAGR), with the Net Margin moving to "&TEXT(Forecast!F22/Forecast!F5,"0.0%")&" from "&TEXT('Overview and Historicals'!$F$19/'Overview and Historicals'!$F$8,"0.0%")&" today." -> Under the Bull scenario, ICICI Bank's consolidated Revenue is projected to grow from ₹1,95,218 Cr (FY25-26) to ₹4,46,571 Cr by FY30-31E (18.0% CAGR), while Net Profit (attributable) grows from ₹54,208 Cr to ₹2,05,517 Cr (30.5% CAGR), with the Net Margin moving to 46.0% from 27.8% today.
B10: 2. What is driving this
B11: • Loan growth is the single biggest swing factor: FY26-31E Revenue CAGR ranges from ~8% (Bear) to ~17% (Bull) purely off the credit-growth assumption — the model is far more sensitive to loan-book growth than to any other single lever.
B13: • Cost-to-income discipline compounds materially over 5 years: a ~3-4pp gap between Base and Bull opex-growth assumptions is worth several percentage points of Net Margin by FY30-31E.
B15: • Minority interest (~4-5% of PBT, from insurance and AMC subsidiaries) is a small but real drag on attributable profit that is easy to overlook if modelling off PBT alone — it is explicitly broken out in this workbook.
B17: • Fee & other income growth (assumed 12.5-17% CAGR range across scenarios) is the second-largest driver of profitability upside, consistent with management's stated focus on strengthening the fee-income mix.
B20: 3. Recommended management actions
B21: • Protect the NIM: keep a disciplined mix of retail/SME/corporate loan growth so margin does not erode as the loan book scales; FCNR(B) deposit mobilisation should be sized so its dilutive NIM impact stays within the Base-case envelope.
B23: • Keep pushing the cost-to-income ratio down: the Bull-vs-Base gap is worth real money by FY30-31E — continue the digital/self-service opex leverage that has driven the FY24-26 improvement.
B25: • Diversify fee income further (distribution, transaction banking, cards) so Other Income growth does not depend solely on a benign credit cycle.
B27: • Hold credit costs and provisioning discipline even in a loan-growth upcycle — the Bear case shows how quickly Net Profit CAGR can invert (to roughly flat-to-negative) if growth slows AND provisioning normalises at the same time.
B29: • Treat the Bear case as the monitoring trigger, not a tail-risk to ignore: track systemic credit growth (currently guided to moderate toward ~14% in FY27) as the single best early-warning indicator for this plan.
B32: 4. Key risks to monitor
... B39: • Minority-interest share of PBT could rise if subsidiaries (insurance, AMC) grow faster than the bank itself, modestly diluting attributable profit growth versus consolidated PBT growth.
